leakradar/__init__.py
leakradar/client.py
leakradar-0.1.6.dist-info/licenses/LICENSE
leakradar-0.1.6.dist-info/METADATA
leakradar-0.1.6.dist-info/WHEEL
leakradar-0.1.6.dist-info/top_level.txt
leakradar-0.1.6.dist-info/RECORD
