Metadata-Version: 2.4
Name: leakradar
Version: 0.1.6
Summary: Asynchronous client for the LeakRadar.io API
Author-email: LeakRadar <contact@leakradar.io>
License: MIT
Classifier: Programming Language :: Python :: 3
Classifier: License :: OSI Approved :: MIT License
Classifier: Operating System :: OS Independent
Requires-Python: >=3.8
License-File: LICENSE
Requires-Dist: httpx>=0.27
Dynamic: license-file
